aniwatch_tr/__init__.py
aniwatch_tr/__main__.py
aniwatch_tr/version.py
aniwatch_tr/api/__init__.py
aniwatch_tr/api/animeci.py
aniwatch_tr/api/o_openani.py
aniwatch_tr/cli/__init__.py
aniwatch_tr/cli/tools_cli.py
aniwatch_tr/core/__init__.py
aniwatch_tr/core/config.py
aniwatch_tr/core/error.py
aniwatch_tr/core/player.py
aniwatch_tr-1.0.2.dist-info/METADATA
aniwatch_tr-1.0.2.dist-info/WHEEL
aniwatch_tr-1.0.2.dist-info/entry_points.txt
aniwatch_tr-1.0.2.dist-info/top_level.txt
aniwatch_tr-1.0.2.dist-info/RECORD
