Metadata-Version: 2.4
Name: aniwatch-tr
Version: 1.0.2
Summary: Türkçe anime izleme ve indirme aracı
Author: https://github.com/DeoDorqnt387/aniwatch-tr
Classifier: Programming Language :: Python :: 3
Classifier: License :: OSI Approved :: GNU General Public License v3 (GPLv3)
Requires-Python: >=3.10
Requires-Dist: requests
Requires-Dist: yt-dlp
Requires-Dist: questionary
Requires-Dist: aria2
Requires-Dist: rich
Requires-Dist: prompt_toolkit
Dynamic: author
Dynamic: classifier
Dynamic: description
Dynamic: description-content-type
Dynamic: requires-dist
Dynamic: requires-python
Dynamic: summary
